Workbook

Sheet Raw Data
A1: Order_ID | B1: Date | C1: Region | D1: Category | E1: Sub_Category | F1: Product_Name | G1: Units_Sold | H1: Unit_Price | I1: Discount_Pct | J1: Revenue | K1: Cost | L1: Profit
A2: NM-1000 | B2: 45422 | C2: Central | D2: Office Supplies | E2: Stationery | F2: Gel Pens | G2: 13 | H2: 21 | I2: 0.05 | J2: =G2*H2*(1-I2) -> 0 | K2: =G2*H2*0.65 -> 0 | L2: =J2-K2 -> 0
A3: NM-1001 | B3: 45606 | C3: East | D3: Electronics | E3: Laptops | F3: HP Spectre | G3: 5 | H3: 128 | I3: 0.05 | J3: =G3*H3*(1-I3) -> 0 | K3: =G3*H3*0.65 -> 0 | L3: =J3-K3 -> 0
A4: NM-1002 | B4: 44683 | C4: Central | D4: Furniture | E4: Storage | F4: File Cabinet | G4: 4 | H4: 69 | I4: 0 | J4: =G4*H4*(1-I4) -> 0 | K4: =G4*H4*0.65 -> 0 | L4: =J4-K4 -> 0
A5: NM-1003 | B5: 45028 | C5: Central | D5: Office Supplies | E5: Binders | F5: File Organizer | G5: 1 | H5: 43 | I5: 0 | J5: =G5*H5*(1-I5) -> 0 | K5: =G5*H5*0.65 -> 0 | L5: =J5-K5 -> 0
A6: NM-1004 | B6: 44892 | C6: Central | D6: Electronics | E6: Phones | F6: Samsung S23 | G6: 5 | H6: 734 | I6: 0 | J6: =G6*H6*(1-I6) -> 0 | K6: =G6*H6*0.65 -> 0 | L6: =J6-K6 -> 0
A7: NM-1005 | B7: 44649 | C7: Central | D7: Office Supplies | E7: Stationery | F7: Notebooks | G7: 10 | H7: 77 | I7: 0.05 | J7: =G7*H7*(1-I7) -> 0 | K7: =G7*H7*0.65 -> 0 | L7: =J7-K7 -> 0
A8: NM-1006 | B8: 45433 | C8: South | D8: Furniture | E8: Tables | F8: Dining Table | G8: 5 | H8: 138 | I8: 0 | J8: =G8*H8*(1-I8) -> 0 | K8: =G8*H8*0.65 -> 0 | L8: =J8-K8 -> 0
A9: NM-1007 | B9: 44692 | C9: South | D9: Electronics | E9: Phones | F9: OnePlus 11 | G9: 4 | H9: 113 | I9: 0.15 | J9: =G9*H9*(1-I9) -> 0 | K9: =G9*H9*0.65 -> 0 | L9: =J9-K9 -> 0
A10: NM-1008 | B10: 45331 | C10: East | D10: Furniture | E10: Tables | F10: Side Table | G10: 6 | H10: 85 | I10: 0.1 | J10: =G10*H10*(1-I10) -> 0 | K10: =G10*H10*0.65 -> 0 | L10: =J10-K10 -> 0
A11: NM-1009 | B11: 44905 | C11: North | D11: Furniture | E11: Tables | F11: Dining Table | G11: 10 | H11: 78 | I11: 0.05 | J11: =G11*H11*(1-I11) -> 0 | K11: =G11*H11*0.65 -> 0 | L11: =J11-K11 -> 0
A12: NM-1010 | B12: 45367 | C12: Central | D12: Electronics | E12: Accessories | F12: Keyboard | G12: 4 | H12: 42 | I12: 0 | J12: =G12*H12*(1-I12) -> 0 | K12: =G12*H12*0.65 -> 0 | L12: =J12-K12 -> 0
A13: NM-1011 | B13: 44947 | C13: North | D13: Electronics | E13: Phones | F13: OnePlus 11 | G13: 14 | H13: 90 | I13: 0.1 | J13: =G13*H13*(1-I13) -> 0 | K13: =G13*H13*0.65 -> 0 | L13: =J13-K13 -> 0
... A551: NM-1549 | B551: 45270 | C551: West | D551: Office Supplies | E551: Binders | F551: 3-Ring Binder | G551: 13 | H551: 61 | I551: 0 | J551: =G551*H551*(1-I551) -> 0 | K551: =G551*H551*0.65 -> 0 | L551: =J551-K551 -> 0

Sheet Data Cleaning
A1: Step | B1: Description | C1: Formula/Action
A2: Trim Whitespace | B2: Removed leading/trailing spaces from Product_Name | C2: =TRIM(F2) -> 0
A3: Handle Errors | B3: Used IFERROR to manage missing price lookups | C3: =IFERROR(VLOOKUP(F2, PriceTable, 2, 0), 0) -> 0
A4: Profit Margin | B4: Calculate Margin % at row level | C4: =IFERROR(L2/J2, 0) -> 0
A5: Remove Duplicates | B5: Standard data hygiene for Order_ID | C5: Data -> Remove Duplicates
A6: Consistency | B6: Ensure Region capitalization is uniform | C6: =UPPER(C2) -> 0

Sheet Analysis
A1: Category | B1: Total Revenue
A2: Electronics | B2: =SUMIFS('Raw Data'!$J$2:$J$551, 'Raw Data'!$D$2:$D$551, A2) -> 0
A3: Furniture | B3: =SUMIFS('Raw Data'!$J$2:$J$551, 'Raw Data'!$D$2:$D$551, A3) -> 0
A4: Office Supplies | B4: =SUMIFS('Raw Data'!$J$2:$J$551, 'Raw Data'!$D$2:$D$551, A4) -> 0

Sheet KPI Summary
A2: Total Revenue | B2: =SUM('Raw Data'!J:J) -> 0
A3: Total Profit | B3: =SUM('Raw Data'!L:L) -> 0
A4: Overall Profit Margin | B4: =B3/B2 -> 0
A5: Average Order Value | B5: =AVERAGE('Raw Data'!J:J) -> 0

Sheet Charts

Sheet Dashboard
A1: NovaMart Performance Dashboard
B5: Total Revenue | D5: Total Profit | F5: Profit Margin
B6: ='KPI Summary'!B2 -> 0 | D6: ='KPI Summary'!B3 -> 0 | F6: ='KPI Summary'!B4 -> 0
